{
  "version": 2,
  "extractor": "pdffigures2",
  "figures": [
    {
      "url": "assets/figures/arxiv/2603.27155v1/fig-001.webp",
      "caption": "Fig. 1. Illustration for Example 1. Liability values are displayed alongside the corresponding arrows, shown in parenthesis for Figures (b)–(d). Initial endowments are depicted within the circles representing the banks. Figures (b), (c), and (d) show clearing vectors where the compression value along the cycle (𝑐1, 𝑐2, 𝑐3) is 𝜀 = 0, 1, 2, respectively, with the payment values written before the liabilities (after compression) in parenthesis.",
      "page": 8,
      "index": 1,
      "width": 814,
      "height": 291
    },
    {
      "url": "assets/figures/arxiv/2603.27155v1/fig-002.webp",
      "caption": "Fig. 2. Visual representation of our results. The plots show the number of defaulting banks for various sample sizes. Results for the baseline, greedy, and MILP methods are shown in grey, red, and blue, respectively. In Figure (a), the red and grey lines overlap almost completely, showing the almost identical performance of the baseline and the greedy methods. The colored “zones” represent the 95% confidence intervals.",
      "page": 20,
      "index": 2,
      "width": 827,
      "height": 317
    }
  ]
}