{
  "version": 2,
  "extractor": "pdffigures2",
  "figures": [
    {
      "url": "assets/figures/arxiv/2603.21330v1/fig-001.webp",
      "caption": "Table 2. Performance and risk metrics across benchmarks",
      "page": 7,
      "index": 1,
      "width": 714,
      "height": 216
    },
    {
      "url": "assets/figures/arxiv/2603.21330v1/fig-002.webp",
      "caption": "Fig. 2. Ablation study of DRL-based allocation with and without timing adjustment. Incorporating the timing module improves cumulative performance and moderates drawdown relative to both the base DRL strategy and the SPY benchmark.",
      "page": 7,
      "index": 2,
      "width": 709,
      "height": 377
    },
    {
      "url": "assets/figures/arxiv/2603.21330v1/fig-003.webp",
      "caption": "Fig. 5. Portfolio allocation trajectory under the unified weight-based execution framework during paper trading. The figure illustrates time-varying exposure adjustments across asset groups, demonstrating modular allocation outputs that are directly executable without architectural changes.",
      "page": 10,
      "index": 3,
      "width": 569,
      "height": 324
    },
    {
      "url": "assets/figures/arxiv/2603.21330v1/fig-004.webp",
      "caption": "Fig. 1. FinRL-X Framework: A layered, end-to-end trading architecture that unifies data processing, strategy construction, backtesting, and broker-integrated execution within a consistent pipeline, illustrating the workflow from data ingestion to live execution.",
      "page": 3,
      "index": 4,
      "width": 760,
      "height": 348
    },
    {
      "url": "assets/figures/arxiv/2603.21330v1/fig-005.webp",
      "caption": "Table 3. Performance comparison of representative use cases and benchmark indices (2018–2025).",
      "page": 8,
      "index": 5,
      "width": 710,
      "height": 206
    },
    {
      "url": "assets/figures/arxiv/2603.21330v1/fig-006.webp",
      "caption": "Fig. 3. Backtest performance comparison across representative strategy configurations under the unified weight-centric protocol (January 7, 2018 – October 24, 2025). Results illustrate cumulative portfolio trajectories relative to benchmark references.",
      "page": 8,
      "index": 6,
      "width": 709,
      "height": 377
    },
    {
      "url": "assets/figures/arxiv/2603.21330v1/fig-007.webp",
      "caption": "Fig. 4. Paper trading performance relative to benchmark indices (October 26, 2025 – March 12, 2026), demonstrating deployment-consistent execution under daily rebalancing.",
      "page": 9,
      "index": 7,
      "width": 709,
      "height": 378
    }
  ]
}